{
  "form": {
    "title": "Contact form",
    "method": "POST",
    "action": "/contact",
    "fields": [
      {
        "name": "name",
        "type": "text",
        "label": "Name",
        "placeholder": "Name",
        "required": true
      },
      {
        "name": "email",
        "type": "email",
        "label": "Email",
        "placeholder": "Email",
        "required": true
      },
      {
        "name": "phone",
        "type": "tel",
        "label": "Phone Number",
        "placeholder": "Phone number",
        "required": false
      },
      {
        "name": "message",
        "type": "textarea",
        "label": "Message",
        "placeholder": "Message",
        "required": true,
        "rows": 5
      }
    ],
    "submitText": "Send",
    "successMessage": "Thank you for your message. We'll get back to you soon!",
    "errorMessage": "Sorry, there was an error sending your message. Please try again."
  }
}